{"trial_id": "0125", "hyperparameters": {"space": [{"class_name": "Int", "config": {"name": "units", "default": null, "conditions": [], "min_value": 32, "max_value": 512, "step": 32, "sampling": "linear"}}, {"class_name": "Int", "config": {"name": "num_layers", "default": null, "conditions": [], "min_value": 1, "max_value": 4, "step": 1, "sampling": "linear"}}, {"class_name": "Int", "config": {"name": "units_0", "default": null, "conditions": [], "min_value": 32, "max_value": 512, "step": 32, "sampling": "linear"}}, {"class_name": "Int", "config": {"name": "units_1", "default": null, "conditions": [], "min_value": 32, "max_value": 512, "step": 32, "sampling": "linear"}}, {"class_name": "Int", "config": {"name": "units_2", "default": null, "conditions": [], "min_value": 32, "max_value": 512, "step": 32, "sampling": "linear"}}, {"class_name": "Int", "config": {"name": "units_3", "default": null, "conditions": [], "min_value": 32, "max_value": 512, "step": 32, "sampling": "linear"}}], "values": {"units": 96, "num_layers": 4, "units_0": 192, "units_1": 384, "units_2": 256, "units_3": 128, "tuner/epochs": 4, "tuner/initial_epoch": 2, "tuner/bracket": 4, "tuner/round": 1, "tuner/trial_id": "0013"}}, "metrics": {"metrics": {"loss": {"direction": "min", "observations": [{"value": [0.5052348375320435], "step": 1}]}, "val_loss": {"direction": "min", "observations": [{"value": [1.9132251739501953], "step": 1}]}}}, "score": 1.9132251739501953, "best_step": 1, "status": "COMPLETED", "message": null}